odoo8_addon_account_fiscal_position_rule_stock-8.0.1.0.0.99.dev3-py3.8-nspkg.pth
odoo_addons/account_fiscal_position_rule_stock/README.rst
odoo_addons/account_fiscal_position_rule_stock/__init__.py
odoo_addons/account_fiscal_position_rule_stock/__openerp__.py
odoo_addons/account_fiscal_position_rule_stock/i18n/account_fiscal_position_rule_stock.pot
odoo_addons/account_fiscal_position_rule_stock/i18n/en_US.po
odoo_addons/account_fiscal_position_rule_stock/i18n/pt_BR.po
odoo_addons/account_fiscal_position_rule_stock/models/__init__.py
odoo_addons/account_fiscal_position_rule_stock/models/stock_picking.py
odoo_addons/account_fiscal_position_rule_stock/security/ir.model.access.csv
odoo_addons/account_fiscal_position_rule_stock/static/description/icon.png
odoo_addons/account_fiscal_position_rule_stock/tests/account_fiscal_position_rule_stock_test.yml
odoo_addons/account_fiscal_position_rule_stock/tests/invoice_from_picking_test.yml
odoo_addons/account_fiscal_position_rule_stock/tests/sale_order_test.yml
odoo_addons/account_fiscal_position_rule_stock/views/stock_picking.xml
odoo8_addon_account_fiscal_position_rule_stock-8.0.1.0.0.99.dev3.dist-info/METADATA
odoo8_addon_account_fiscal_position_rule_stock-8.0.1.0.0.99.dev3.dist-info/WHEEL
odoo8_addon_account_fiscal_position_rule_stock-8.0.1.0.0.99.dev3.dist-info/namespace_packages.txt
odoo8_addon_account_fiscal_position_rule_stock-8.0.1.0.0.99.dev3.dist-info/top_level.txt
odoo8_addon_account_fiscal_position_rule_stock-8.0.1.0.0.99.dev3.dist-info/RECORD
